myapp0/__init__.py
myapp0/mycode.py
mayapp0-1.0.0.dist-info/METADATA
mayapp0-1.0.0.dist-info/WHEEL
mayapp0-1.0.0.dist-info/top_level.txt
mayapp0-1.0.0.dist-info/RECORD
